privacyscanner/__init__.py
privacyscanner/defaultconfig.py
privacyscanner/exceptions.py
privacyscanner/filehandlers.py
privacyscanner/jobqueue.py
privacyscanner/loghandlers.py
privacyscanner/raven.py
privacyscanner/result.py
privacyscanner/scanmeta.py
privacyscanner/scanner.py
privacyscanner/worker.py
privacyscanner/scanmodules/__init__.py
privacyscanner/scanmodules/dns.py
privacyscanner/scanmodules/example.py
privacyscanner/scanmodules/mail.py
privacyscanner/scanmodules/serverleaks.py
privacyscanner/scanmodules/chromedevtools/__init__.py
privacyscanner/scanmodules/chromedevtools/chromescan.py
privacyscanner/scanmodules/chromedevtools/utils.py
privacyscanner/scanmodules/chromedevtools/extractors/__init__.py
privacyscanner/scanmodules/chromedevtools/extractors/base.py
privacyscanner/scanmodules/chromedevtools/extractors/certificate.py
privacyscanner/scanmodules/chromedevtools/extractors/cookies.py
privacyscanner/scanmodules/chromedevtools/extractors/cookiestats.py
privacyscanner/scanmodules/chromedevtools/extractors/failedrequests.py
privacyscanner/scanmodules/chromedevtools/extractors/finalurl.py
privacyscanner/scanmodules/chromedevtools/extractors/fingerprinting.py
privacyscanner/scanmodules/chromedevtools/extractors/googleanalytics.py
privacyscanner/scanmodules/chromedevtools/extractors/hstspreload.py
privacyscanner/scanmodules/chromedevtools/extractors/imprint.py
privacyscanner/scanmodules/chromedevtools/extractors/insecurecontent.py
privacyscanner/scanmodules/chromedevtools/extractors/javascriptlibs.py
privacyscanner/scanmodules/chromedevtools/extractors/redirectchain.py
privacyscanner/scanmodules/chromedevtools/extractors/requests.py
privacyscanner/scanmodules/chromedevtools/extractors/screenshot.py
privacyscanner/scanmodules/chromedevtools/extractors/securityheaders.py
privacyscanner/scanmodules/chromedevtools/extractors/thirdparties.py
privacyscanner/scanmodules/chromedevtools/extractors/tlsdetails.py
privacyscanner-0.8.0.dist-info/LICENSE
privacyscanner-0.8.0.dist-info/METADATA
privacyscanner-0.8.0.dist-info/WHEEL
privacyscanner-0.8.0.dist-info/entry_points.txt
privacyscanner-0.8.0.dist-info/top_level.txt
privacyscanner-0.8.0.dist-info/RECORD
