Metadata-Version: 2.1
Name: privacyscanner
Version: 0.8.0
Summary: Privacyscanner scans websites for security and privacy properties. It is the future scanning engine of PrivacyScore.
Home-page: https://github.com/PrivacyScore/privacyscanner
Author: PrivacyScore developers
Author-email: privacyscore.psi@uni-bamberg.de
License: MIT
Keywords: privacy,security,scanner,scan,privacyscore,privacyscanner
Platform: any
Classifier: Development Status :: 4 - Beta
Classifier: License :: OSI Approved :: MIT License
Classifier: Programming Language :: Python :: 3
Classifier: Programming Language :: Python :: 3.6
Classifier: Programming Language :: Python :: 3.7
Requires-Python: >= 3.6
Requires-Dist: adblockeval
Requires-Dist: cryptography
Requires-Dist: dnspython
Requires-Dist: geoip2
Requires-Dist: pillow
Requires-Dist: psutil
Requires-Dist: psycopg2-binary
Requires-Dist: pychrome
Requires-Dist: requests
Requires-Dist: tldextract
Requires-Dist: toposort
